dcgan_implementation/__init__.py
dcgan_implementation/__main__.py
dcgan_implementation/dataset.py
dcgan_implementation/discriminator.py
dcgan_implementation/generator.py
dcgan_implementation/metrics.py
dcgan_implementation/utils.py
dcgan_implementation-0.1.0.dist-info/entry_points.txt
dcgan_implementation-0.1.0.dist-info/LICENSE
dcgan_implementation-0.1.0.dist-info/WHEEL
dcgan_implementation-0.1.0.dist-info/METADATA
dcgan_implementation-0.1.0.dist-info/RECORD
