Metadata-Version: 2.1
Name: dcgan-implementation
Version: 0.1.0
Summary: Simple DCGAN implementation for experimenting
License: MIT
Author: Andy Jackson
Author-email: amjack100@gmail.com
Requires-Python: >=3.7,<4.0
Classifier: License :: OSI Approved :: MIT License
Classifier: Programming Language :: Python :: 3
Classifier: Programming Language :: Python :: 3.7
Classifier: Programming Language :: Python :: 3.8
Classifier: Programming Language :: Python :: 3.9
Requires-Dist: fire (>=0.4.0,<0.5.0)
Requires-Dist: imageio (>=2.9.0,<3.0.0)
Requires-Dist: matplotlib (>=3.3.4,<4.0.0)
Requires-Dist: tensorflow (>=2.4.1,<3.0.0)
